<?xml version="1.0" encoding="UTF-8" standalone="no"?>
<!DOCTYPE Model SYSTEM "/opt/ericsson/arne/etc/arne10_1.dtd">

<!--~~~~~~~~~~~~~~~~~~~~~~~~~~~~~~~~~~~~~~~~~~~~~~~~~~~-->
<!--                IMPORTANT NOTE                     -->
<!--~~~~~~~~~~~~~~~~~~~~~~~~~~~~~~~~~~~~~~~~~~~~~~~~~~~-->

<!--These sample xml files are provided as examples of
    what an import file should look like. They have been 
    tested against the following tck packages. 
    
    TCKC => R7F03
    TCKW => R3A02
    TCKG => R3A01
    
    If you are importing using different versions of tck then
    you will have to update the import files
-->
<!--~~~~~~~~~~~~~~~~~~~~~~~~~~~~~~~~~~~~~~~~~~~~~~~~~~~-->

<Model version="1" importVersion="10.1">
  <Delete>
     <Object fdn="SubNetwork=REPLACE,MeContext=CMSAutoRXI,ManagedElement=1"/>
     <Object fdn="SubNetwork=REPLACE,MeContext=CMSAutoERBS,ManagedElement=1"/>
     <Object fdn="SubNetwork=REPLACE,SubNetwork=CMSAuto,MeContext=CMSAutoRBS,ManagedElement=1"/>
     <Object fdn="SubNetwork=REPLACE,SubNetwork=CMSAuto,Group=Fesh"/>
     <Object fdn="SubNetwork=REPLACE,SubNetwork=CMSAuto,MeContext=CMSAuto,ManagedElement=1"/>
     <Object fdn="SubNetwork=REPLACE,SubNetwork=CMSAuto"/>
  </Delete>  
</Model>
